unconscious-0.0.13.dist-info/METADATA
unconscious-0.0.13.dist-info/WHEEL
unconscious-0.0.13.dist-info/entry_points.txt
unconscious/agent.py
unconscious/client.py
unconscious/__init__.py
unconscious/_unconscious.cpython-311-x86_64-linux-gnu.so
unconscious-0.0.13.dist-info/RECORD
