Metadata-Version: 2.3
Name: unconscious
Version: 0.0.13
Classifier: Programming Language :: Rust
Classifier: Programming Language :: Python :: Implementation :: CPython
Classifier: Programming Language :: Python :: Implementation :: PyPy
Requires-Dist: typer ==0.12.3
Requires-Dist: sseclient ==0.0.27
Requires-Dist: requests ==2.32.3
Requires-Dist: toml ==0.10.2
Requires-Python: >=3.8
